sdk/authorization_tag.py
sdk/autobahn_charging_station.py
sdk/autobahn_charging_station_collection.py
sdk/autobahn_charging_station_tag.py
sdk/autobahn_closure.py
sdk/autobahn_closure_collection.py
sdk/autobahn_closure_tag.py
sdk/autobahn_collection.py
sdk/autobahn_coordinate.py
sdk/autobahn_parking_lorry.py
sdk/autobahn_parking_lorry_collection.py
sdk/autobahn_parking_lorry_tag.py
sdk/autobahn_tag.py
sdk/autobahn_warning.py
sdk/autobahn_warning_collection.py
sdk/autobahn_warning_tag.py
sdk/backend_app.py
sdk/backend_token.py
sdk/backend_user.py
sdk/bundesrat_member.py
sdk/bundesrat_member_collection.py
sdk/bundesrat_member_tag.py
sdk/bundesrat_tag.py
sdk/bundestag_constituency.py
sdk/bundestag_member.py
sdk/bundestag_member_collection.py
sdk/bundestag_member_tag.py
sdk/bundestag_tag.py
sdk/city.py
sdk/city_collection.py
sdk/city_tag.py
sdk/client.py
sdk/collection.py
sdk/common_message.py
sdk/common_message_exception.py
sdk/common_metadata.py
sdk/district.py
sdk/district_collection.py
sdk/district_tag.py
sdk/hospital.py
sdk/hospital_collection.py
sdk/hospital_tag.py
sdk/job.py
sdk/job_collection.py
sdk/job_coordinate.py
sdk/job_location.py
sdk/job_tag.py
sdk/meta_tag.py
sdk/response.py
sdk/response_exception.py
sdk/state.py
sdk/state_collection.py
sdk/state_tag.py
sdk/system_about.py
sdk/system_about_apps.py
sdk/system_about_link.py
sdk/warning.py
sdk/warning_collection.py
sdk/warning_tag.py
deutschland_api_sdk-0.1.4.dist-info/LICENSE
deutschland_api_sdk-0.1.4.dist-info/METADATA
deutschland_api_sdk-0.1.4.dist-info/WHEEL
deutschland_api_sdk-0.1.4.dist-info/top_level.txt
deutschland_api_sdk-0.1.4.dist-info/RECORD
