Metadata-Version: 2.1
Name: deutschland-api-sdk
Version: 0.1.4
Summary: Client SDK to access the Deutschland API
Author-email: Christoph Kappestein <christoph.kappestein@gmail.com>
License: MIT
Project-URL: Homepage, https://github.com/apioo/deutschland-api-sdk-python
Project-URL: Issues, https://github.com/apioo/deutschland-api-sdk-python/issues
Classifier: Programming Language :: Python :: 3
Classifier: License :: OSI Approved :: MIT License
Classifier: Operating System :: OS Independent
Classifier: Topic :: Software Development :: Code Generators
Requires-Python: >=3.8
License-File: LICENSE
Requires-Dist: sdkgen-client
